simplifiedpytrends/__init__.py
simplifiedpytrends/exceptions.py
simplifiedpytrends/request.py
simplifiedpytrends/test_trendReq.py
simplifiedpytrends-1.1.2.dist-info/LICENSE
simplifiedpytrends-1.1.2.dist-info/METADATA
simplifiedpytrends-1.1.2.dist-info/WHEEL
simplifiedpytrends-1.1.2.dist-info/top_level.txt
simplifiedpytrends-1.1.2.dist-info/RECORD
