Metadata-Version: 2.1
Name: simplifiedpytrends
Version: 1.1.2
Summary: Simplified Pseudo API for Google Trends
Home-page: https://github.com/Drakkar-Software/pytrends
Author: ['John Hogue', 'Burton DeWilde', 'DrakkarSoftware']
Author-email: drakkar.software@protonmail.com
License: Apache 2.0
Keywords: google trends api search
Platform: UNKNOWN
Classifier: Development Status :: 4 - Beta
Classifier: Intended Audience :: Developers
Classifier: Programming Language :: Python :: 2.7
Classifier: Programming Language :: Python :: 3.3
Classifier: Programming Language :: Python :: 3.4
Classifier: Programming Language :: Python :: 3.5
Classifier: Programming Language :: Python :: 3.6
Classifier: Programming Language :: Python :: 3.7
Classifier: License :: OSI Approved :: MIT License
Requires-Dist: requests
Requires-Dist: aiohttp
